geoloc/__init__.py
geoloc/datamodels/__pycache__/base_model.cpython-311.pyc
geoloc/datamodels/__pycache__/location_info.cpython-311.pyc
geoloc/datamodels/base_model.py
geoloc/datamodels/location_info.py
geoloc/geoloc_util.py
geoloc/logger/__pycache__/log_utils.cpython-311.pyc
geoloc/logger/log_utils.py
geoloc/services/__pycache__/geoloc_services.cpython-311.pyc
geoloc/services/geoloc_services.py
geoloc/utils/__pycache__/api_utils.cpython-311.pyc
geoloc/utils/__pycache__/common_utils.cpython-311.pyc
geoloc/utils/api_utils.py
geoloc/utils/common_utils.py
geoloc-0.1.1.dist-info/LICENSE
geoloc-0.1.1.dist-info/METADATA
geoloc-0.1.1.dist-info/WHEEL
geoloc-0.1.1.dist-info/entry_points.txt
geoloc-0.1.1.dist-info/RECORD
