Metadata-Version: 2.3
Name: geoloc
Version: 0.1.1
Summary: A CLI tool for geographical location utilities.
License: MIT
Author: swami.padmanabhan
Author-email: swami.padman@gmail.com
Requires-Python: >=3.11,<3.12
Classifier: License :: OSI Approved :: MIT License
Classifier: Programming Language :: Python :: 3
Classifier: Programming Language :: Python :: 3.11
Requires-Dist: click (==8.1.7)
Requires-Dist: pydantic (==2.10.6)
Requires-Dist: pytest (==8.3.4)
Requires-Dist: pytest-mock (==3.14.0)
Requires-Dist: requests (==2.32.3)
